causalgraph/__init__.py
causalgraph/graph.py
causalgraph/store/__init__.py
causalgraph/store/add.py
causalgraph/store/edit.py
causalgraph/store/export.py
causalgraph/store/load.py
causalgraph/store/remove.py
causalgraph/utils/__init__.py
causalgraph/utils/draw.py
causalgraph/utils/logging_utils.py
causalgraph/utils/mapping.py
causalgraph/utils/misc_utils.py
causalgraph/utils/owlready2_utils.py
data/__init__.py
data/causalgraph.owl
data/logs/__init__.py
causalgraph-0.1.1.dist-info/LICENSE
causalgraph-0.1.1.dist-info/METADATA
causalgraph-0.1.1.dist-info/WHEEL
causalgraph-0.1.1.dist-info/top_level.txt
causalgraph-0.1.1.dist-info/RECORD
