Metadata-Version: 2.1
Name: causalgraph
Version: 0.1.1
Summary: A python package for modeling, persisting and visualizing causal graphs embedded in knowledge graphs.
Author: Fraunhofer IWU
Author-email: causalgraph@iwu.fraunhofer.de
License: MIT
Classifier: Programming Language :: Python :: 3.9
Classifier: Programming Language :: Python :: 3.10
License-File: LICENSE
Requires-Dist: owlready2 ==0.43
Requires-Dist: networkx ==2.8.4
Requires-Dist: matplotlib ==3.5.1
Requires-Dist: ecs-logging ==1.1.0
Requires-Dist: numpy ==1.23.5
Requires-Dist: deprecated ==1.2.14
